liteflow/__init__.py
liteflow/context.py
liteflow/executor.py
liteflow/flow.py
liteflow/state.py
liteflow-0.2.0.dist-info/LICENSE
liteflow-0.2.0.dist-info/METADATA
liteflow-0.2.0.dist-info/WHEEL
liteflow-0.2.0.dist-info/RECORD
