Metadata-Version: 2.3
Name: liteflow
Version: 0.2.0
Summary: Lightweight task flow framework for Python
License: LICENSE
Author: Meta42
Requires-Python: >=3.9,<4
Classifier: License :: Other/Proprietary License
Classifier: Programming Language :: Python :: 3
Classifier: Programming Language :: Python :: 3.9
Classifier: Programming Language :: Python :: 3.10
Classifier: Programming Language :: Python :: 3.11
Classifier: Programming Language :: Python :: 3.12
Classifier: Programming Language :: Python :: 3.13
Provides-Extra: ray
Requires-Dist: lmnr (>=0.4.62,<0.5.0)
Project-URL: Repository, https://github.com/iodone/pyflow
